enterprise_models/__init__.py
enterprise_models/apps.py
enterprise_models/models.py
enterprise_models/migrations/0001_initial.py
enterprise_models/migrations/0002_contractor_contractor_number_and_more.py
enterprise_models/migrations/__init__.py
enterprise_models-0.1.9.dist-info/METADATA
enterprise_models-0.1.9.dist-info/WHEEL
enterprise_models-0.1.9.dist-info/top_level.txt
enterprise_models-0.1.9.dist-info/RECORD
