Metadata-Version: 2.4
Name: enterprise-models
Version: 0.1.9
Summary: My Django models package
Author-email: Mani Kanta Kotla <your@email.com>
Requires-Python: >=3.11
Requires-Dist: django>=5.0
